[{"data": {
    "type": "LinkChart",
    "items": [
      {
        "id": "1",
        "type": "node",
        "t": "splunkd.exe",
        "d": {
          "labels": [
            "Process"
          ]
        }
      },
{
        "dt": [
          1588935003000,
          1588935303000,
          1588936089000,
          1588935735000,
          1588935608000,
          1588935849000,
          1588935428000,
          1588935787000,
          1588935065000,
          1588935975000,
          1588935241000,
          1588935127000,
          1588935912000,
          1588935189000,
          1588935492000,
          1588936026000,
          1588935365000,
          1588935555000,
          1588936151000,
          1588935671000
        ],
        "a2": true,
        "id1": "1",
        "id2": "195",
        "id": "196",
        "type": "link",
        "t": "Create Process",
        "d": {
          "labels": "",
          "ids": [
            "196",
            "199",
            "1398",
            "1401",
            "1404",
            "1407",
            "1410",
            "1413",
            "1416",
            "1419",
            "1422",
            "1425",
            "1428",
            "1431",
            "1434",
            "1437",
            "1440",
            "1443",
            "1446",
            "1449"
          ]
        }
      },
{
        "dt": [
          1588935964000,
          1588936026000,
          1588935303000,
          1588935003000,
          1588935003000,
          1588936089000,
          1588935418000,
          1588935418000,
          1588935724000,
          1588935127000,
          1588935127000,
          1588935608000,
          1588935608000,
          1588935787000,
          1588935065000,
          1588935065000,
          1588935241000,
          1588935241000,
          1588935179000,
          1588935179000,
          1588935492000,
          1588935492000,
          1588935303000,
          1588935365000,
          1588936026000,
          1588935849000,
          1588936078000,
          1588935555000,
          1588935555000,
          1588935901000,
          1588935365000,
          1588935787000,
          1588935964000,
          1588935901000,
          1588936141000,
          1588936141000,
          1588935839000,
          1588935724000,
          1588935661000,
          1588935661000
        ],
        "a2": true,
        "id1": "1",
        "id2": "165",
        "id": "166",
        "type": "link",
        "t": "Create Process",
        "d": {
          "labels": "",
          "ids": [
            "166",
            "169",
            "1284",
            "1287",
            "1290",
            "1293",
            "1296",
            "1299",
            "1302",
            "1305",
            "1308",
            "1311",
            "1314",
            "1317",
            "1320",
            "1323",
            "1326",
            "1329",
            "1332",
            "1335",
            "1338",
            "1341",
            "1344",
            "1347",
            "1350",
            "1353",
            "1356",
            "1359",
            "1362",
            "1365",
            "1368",
            "1371",
            "1374",
            "1377",
            "1380",
            "1383",
            "1386",
            "1389",
            "1392",
            "1395"
          ]
        }
      },
{
        "dt": [
          1588935964000,
          1588936026000,
          1588935555000,
          1588935303000,
          1588935003000,
          1588935127000,
          1588935608000,
          1588936078000,
          1588935428000,
          1588935787000,
          1588935065000,
          1588935241000,
          1588935492000,
          1588935901000,
          1588935365000,
          1588935189000,
          1588935839000,
          1588936141000,
          1588935724000,
          1588935661000
        ],
        "a2": true,
        "id1": "1",
        "id2": "159",
        "id": "160",
        "type": "link",
        "t": "Create Process",
        "d": {
          "labels": "",
          "ids": [
            "160",
            "163",
            "1230",
            "1233",
            "1236",
            "1239",
            "1242",
            "1245",
            "1248",
            "1251",
            "1254",
            "1257",
            "1260",
            "1263",
            "1266",
            "1269",
            "1272",
            "1275",
            "1278",
            "1281"
          ]
        }
      },
{
        "dt": [
          1588935901000,
          1588935055000,
          1588935241000,
          1588935777000,
          1588935597000,
          1588935355000,
          1588935492000,
          1588935179000,
          1588935418000,
          1588936078000,
          1588935954000,
          1588936141000,
          1588936192000,
          1588935293000,
          1588935534000,
          1588935661000,
          1588935839000,
          1588935116000,
          1588936016000,
          1588935714000
        ],
        "a2": true,
        "id1": "1",
        "id2": "14",
        "id": "15",
        "type": "link",
        "t": "Create Process",
        "d": {
          "labels": "",
          "ids": [
            "15",
            "18",
            "1176",
            "1179",
            "1182",
            "1185",
            "1188",
            "1191",
            "1194",
            "1197",
            "1200",
            "1203",
            "1206",
            "1209",
            "1212",
            "1215",
            "1218",
            "1221",
            "1224",
            "1227"
          ]
        }
      },
{
        "dt": [
          1588935055000,
          1588935901000,
          1588935003000,
          1588935418000,
          1588935303000,
          1588935777000,
          1588935116000,
          1588936016000,
          1588935355000,
          1588935492000,
          1588935241000,
          1588935179000,
          1588935545000,
          1588935597000,
          1588936141000,
          1588935661000,
          1588935839000,
          1588936078000,
          1588935954000,
          1588935724000
        ],
        "a2": true,
        "id1": "1",
        "id2": "5",
        "id": "6",
        "type": "link",
        "t": "Create Process",
        "d": {
          "labels": "",
          "ids": [
            "6",
            "12",
            "1122",
            "1125",
            "1128",
            "1131",
            "1134",
            "1137",
            "1140",
            "1143",
            "1146",
            "1149",
            "1152",
            "1155",
            "1158",
            "1161",
            "1164",
            "1167",
            "1170",
            "1173"
          ]
        }
      },
{
        "dt": [
          1588935003000,
          1588936036000,
          1588936151000,
          1588935303000,
          1588936089000,
          1588935735000,
          1588935608000,
          1588935849000,
          1588935787000,
          1588935065000,
          1588935428000,
          1588935251000,
          1588935127000,
          1588935365000,
          1588935975000,
          1588935912000,
          1588935189000,
          1588935492000,
          1588935555000,
          1588935671000
        ],
        "a2": true,
        "id1": "1",
        "id2": "2",
        "id": "3",
        "type": "link",
        "t": "Create Process",
        "d": {
          "labels": "",
          "ids": [
            "3",
            "9",
            "1068",
            "1071",
            "1074",
            "1077",
            "1080",
            "1083",
            "1086",
            "1089",
            "1092",
            "1095",
            "1098",
            "1101",
            "1104",
            "1107",
            "1110",
            "1113",
            "1116",
            "1119"
          ]
        }
      },
{
        "id": "195",
        "type": "node",
        "t": "splunk-regmon.exe",
        "d": {
          "labels": [
            "Process"
          ]
        }
      },
{
        "id": "165",
        "type": "node",
        "t": "splunk-powershell.exe",
        "d": {
          "labels": [
            "Process"
          ]
        }
      },
{
        "id": "159",
        "type": "node",
        "t": "splunk-netmon.exe",
        "d": {
          "labels": [
            "Process"
          ]
        }
      },
{
        "id": "2",
        "type": "node",
        "t": "splunk-winprintmon.exe",
        "d": {
          "labels": [
            "Process"
          ]
        }
      },
{
        "id": "14",
        "type": "node",
        "t": "splunk-MonitorNoHandle.exe",
        "d": {
          "labels": [
            "Process"
          ]
        }
      },
{
        "id": "5",
        "type": "node",
        "t": "splunk-admon.exe",
        "d": {
          "labels": [
            "Process"
          ]
        }
      }
]
}}]